magic/__init__.py
magic/__init__.pyi
magic/compat.py
magic/loader.py
magic/py.typed
python_magic-0.4.25.dist-info/LICENSE
python_magic-0.4.25.dist-info/METADATA
python_magic-0.4.25.dist-info/WHEEL
python_magic-0.4.25.dist-info/top_level.txt
python_magic-0.4.25.dist-info/RECORD
